{
"01":"Telstra Corporation Ltd.",
"02":"Optus Mobile Pty. Ltd.",
"03":"Vodafone Network Pty. Ltd.",
"04":"Department of Defence",
"05":"The Ozitel Network Pty. Ltd.",
"06":"Hutchison 3G Australia Pty. Ltd.",
"07":"Vodafone Network Pty. Ltd.",
"08":"One.Tel GSM 1800 Pty. Ltd.",
"09":"Airnet Commercial Australia Ltd.",
"10":"Norfolk Telecom",
"11":"Telstra Corporation Ltd.",
"12":"Hutchison Telecommunications (Australia) Pty. Ltd.",
"13":"Railcorp",
"14":"AAPT Ltd",
"15":"3GIS Pty Ltd. (Telstra & Hutchison 3G)",
"16":"Victorian Rail Track",
"17":"Vivid Wireless Pty Ltd",
"18":"Pactel International Pty Ltd",
"19":"Lycamobile Pty Ltd",
"20":"Ausgrid Corporation",
"21":"Queensland Rail Limited",
"22":"iiNet Ltd",
"23":"Challenge Networks Pty Ltd",
"24":"Advanced Communications Technologies Pty. Ltd.",
"25":"Pilbara Iron Company Services Pty Ltd",
"26":"Dialogue Communications Pty Ltd",
"27":"Nexium Telecommunications",
"28":"RCOM International Pty Ltd",
"30":"Compatel Limited",
"31":"BHP Billiton",
"32":"Thales Australia",
"33":"CLX Networks Pty Ltd",
"34":"Santos Ltd",
"35":"MessageBird Pty Ltd",
"36":"Optus Mobile Pty. Ltd.",
"37":"Yancoal Australia Ltd",
"38":"Truphone Pty Ltd",
"39":"Telstra Corporation Ltd.",
"40":"CITIC PACIFIC MINING",
"41":"Aqura Technologies Pty",
"42":"Groote Eylandt Mining Company Pty Ltd",
"43":"Arrow Energy Pty Ltd",
"44":"ROY HILL IRON ORE PTY LTD",
"45":"CLERMONT COAL OPERATIONS PTY Limited",
"50":"Pivotel Group Pty Limited",
"61":"Commtel Network Solutions Pty Ltd",
"62":"NBNCo Limited",
"68":"NBNCo Limited",
"71":"Telstra Corporation Ltd.",
"72":"Telstra Corporation Ltd.",
"88":"Pivotel Group Pty Limited",
"90":"Optus Ltd.",
"99":"One.Tel GSM 1800 Pty. Ltd."
}